uncch_camri/__init__.py
uncch_camri/interface.py
uncch_camri/pipeline.py
pynipt_plugin_uncch_camri-0.0.1.dist-info/METADATA
pynipt_plugin_uncch_camri-0.0.1.dist-info/WHEEL
pynipt_plugin_uncch_camri-0.0.1.dist-info/top_level.txt
pynipt_plugin_uncch_camri-0.0.1.dist-info/RECORD
